README.md
setup.py
icli/__init__.py
icli.egg-info/PKG-INFO
icli.egg-info/SOURCES.txt
icli.egg-info/dependency_links.txt
icli.egg-info/requires.txt
icli.egg-info/top_level.txt