Metadata-Version: 2.1
Name: icli
Version: 0.0.7
Summary: Interactive CLI builder
Home-page: https://github.com/alttch/icli
Author: Altertech
Author-email: div@altertech.com
License: MIT
Platform: UNKNOWN
Classifier: Programming Language :: Python :: 3
Classifier: License :: OSI Approved :: MIT License
Classifier: Topic :: Software Development :: Libraries
Classifier: Topic :: Software Development :: User Interfaces
